ml_copilot_agent/__init__.py
ml_copilot_agent/__main__.py
ml_copilot_agent/workflow.py
ml_copilot_agent-0.1.8.dist-info/LICENSE
ml_copilot_agent-0.1.8.dist-info/METADATA
ml_copilot_agent-0.1.8.dist-info/WHEEL
ml_copilot_agent-0.1.8.dist-info/RECORD
