Metadata-Version: 2.1
Name: ml-copilot-agent
Version: 0.1.8
Summary: "It is a Machine Learning Copilot Agent that can execute code for end-to-end ML Cycle"
License: CC-BY-NC-ND-4.0
Author: VatsalPatel18
Author-email: vatsal1804@gmail.com
Requires-Python: >=3.9,<4.0
Classifier: License :: Other/Proprietary License
Classifier: Programming Language :: Python :: 3
Classifier: Programming Language :: Python :: 3.9
Classifier: Programming Language :: Python :: 3.10
Classifier: Programming Language :: Python :: 3.11
Classifier: Programming Language :: Python :: 3.12
Requires-Dist: llama-index (==0.11.16)
Requires-Dist: llama-index-agent-openai (==0.3.4)
Requires-Dist: llama-index-embeddings-huggingface (==0.3.1)
Requires-Dist: llama-index-llms-huggingface (==0.3.4)
Requires-Dist: llama-index-llms-openai (==0.2.11)
Requires-Dist: llama-index-tools-code-interpreter (==0.2.0)
Requires-Dist: llama-index-utils-workflow (==0.2.1)
Requires-Dist: matplotlib (>=3.7.0)
Requires-Dist: scikit-learn (>=1.2)
Requires-Dist: seaborn (>=0.10)
